kaidoku/__init__.py
kaidoku/calc.py
kaidoku/chain.py
kaidoku/command.py
kaidoku/create.py
kaidoku/gui.py
kaidoku/help.py
kaidoku/image.py
kaidoku/kaidoku.py
kaidoku/main.py
kaidoku/misc.py
kaidoku/output.py
kaidoku/search.py
kaidoku/test.py
kaidoku/wing.py
kaidoku/data/blank-large.eps
kaidoku/data/blank-medium.eps
kaidoku/data/blank-small.eps
kaidoku/data/blank-x-large.eps
kaidoku/data/current.html
kaidoku/data/sudoku.txt
kaidoku/data/system.ini
kaidoku-1.0.1.dist-info/LICENSE.txt
kaidoku-1.0.1.dist-info/METADATA
kaidoku-1.0.1.dist-info/WHEEL
kaidoku-1.0.1.dist-info/entry_points.txt
kaidoku-1.0.1.dist-info/top_level.txt
kaidoku-1.0.1.dist-info/RECORD
