Metadata-Version: 2.1
Name: kaidoku
Version: 1.0.1
Summary: Player, solver and creater of sudoku puzzles
Home-page: https://sekika.github.io/kaidoku/
Author: Katsutoshi Seki
License: MIT
Keywords: sudoku
Classifier: Development Status :: 5 - Production/Stable
Classifier: Intended Audience :: End Users/Desktop
Classifier: Environment :: Console
Classifier: Programming Language :: Python :: 3
Classifier: Programming Language :: Python :: 3.5
Classifier: Programming Language :: Python :: 3.6
Classifier: Programming Language :: Python :: 3.7
Classifier: Programming Language :: Python :: 3.8
Classifier: Programming Language :: Python :: 3.9
Classifier: Programming Language :: Python :: 3.10
Classifier: Programming Language :: JavaScript
Classifier: License :: OSI Approved :: MIT License
Classifier: Operating System :: OS Independent
Classifier: Operating System :: MacOS :: MacOS X
Classifier: Operating System :: Microsoft :: Windows :: Windows 10
Classifier: Operating System :: POSIX
Classifier: Operating System :: POSIX :: BSD
Classifier: Operating System :: POSIX :: Linux
Classifier: Natural Language :: English
Classifier: Natural Language :: Japanese
Classifier: Topic :: Games/Entertainment :: Puzzle Games
Requires-Python: >=3.5
License-File: LICENSE.txt
Requires-Dist: ConfigObj
Requires-Dist: pillow
Requires-Dist: pyx
Requires-Dist: tk
